trove_classifiers/__init__.py
trove_classifiers/__main__.py
trove_classifiers/py.typed
trove_classifiers-2025.9.8.13.dist-info/licenses/LICENSE
trove_classifiers-2025.9.8.13.dist-info/METADATA
trove_classifiers-2025.9.8.13.dist-info/WHEEL
trove_classifiers-2025.9.8.13.dist-info/entry_points.txt
trove_classifiers-2025.9.8.13.dist-info/top_level.txt
trove_classifiers-2025.9.8.13.dist-info/RECORD
