Metadata-Version: 2.4
Name: trove-classifiers
Version: 2025.9.8.13
Summary: Canonical source for classifiers on PyPI (pypi.org).
Home-page: https://github.com/pypa/trove-classifiers
Author: The PyPI Admins
Author-email: admin@pypi.org
Keywords: classifiers
Classifier: Development Status :: 5 - Production/Stable
Classifier: Intended Audience :: Developers
Classifier: License :: OSI Approved :: Apache Software License
Classifier: Programming Language :: Python :: 3
Classifier: Typing :: Typed
License-File: LICENSE
Dynamic: author
Dynamic: author-email
Dynamic: classifier
Dynamic: description
Dynamic: description-content-type
Dynamic: home-page
Dynamic: keywords
Dynamic: license-file
Dynamic: summary
